{"pipelineKey":"ce73f578-022d-4137-a24c-76bc8828552c","name":"Dodge","description":"","definition":"{\"workerLimit\":4,\"selectedEngine\":\"sampleEngine\",\"selectedStopOption\":\"No\",\"tasks\":[{\"children\":[\"DataflowqF9cJ\"],\"iteratee\":{},\"id\":\"Terminator\",\"type\":\"Terminator\"},{\"parent\":[\"Terminator\"],\"stopOnTaskFailure\":\"N\",\"stopOnTaskSuccess\":\"N\",\"dfName\":\"Table_vs_Table\",\"stopDependentTasks\":\"N\",\"label\":\"Data\",\"type\":\"runDataFlow\",\"dfKey\":\"c058dad7-f6cd-4225-a274-8cd7765ee198\",\"livyServer\":\"sampleEngine\",\"children\":[],\"iteratee\":{},\"name\":\"Table_vs_Table\",\"id\":\"DataflowqF9cJ\",\"parameters\":\"{\\\"limit_rows\\\":\\\"limit 1000\\\"}\"}]}"}